pyspark_anonymizer/Parser.py
pyspark_anonymizer/ParserFromDynamoDB.py
pyspark_anonymizer/__init__.py
pyspark_anonymizer-0.5.dist-info/LICENSE
pyspark_anonymizer-0.5.dist-info/METADATA
pyspark_anonymizer-0.5.dist-info/WHEEL
pyspark_anonymizer-0.5.dist-info/top_level.txt
pyspark_anonymizer-0.5.dist-info/RECORD
