Metadata-Version: 2.1
Name: pyspark-anonymizer
Version: 0.5
Summary: Python library which makes it possible to dynamically mask/anonymize data using JSON string or python dict rules in a PySpark environment.
Home-page: https://github.com/wesleywilian/pyspark-anonymizer
Author: wesleywilian
License: apache-2.0
Download-URL: https://github.com/wesleywilian/pyspark-anonymizer/archive/v0.5.tar.gz
Keywords: data anonymizer,anon,spark,data mask,mask,data masking,masking
Platform: UNKNOWN
Classifier: Development Status :: 3 - Alpha
Classifier: Intended Audience :: Developers
Classifier: Topic :: Software Development :: Build Tools
Classifier: License :: OSI Approved :: Apache Software License
Classifier: Programming Language :: Python :: 3
Classifier: Programming Language :: Python :: 3.6
Classifier: Programming Language :: Python :: 3.7
Classifier: Programming Language :: Python :: 3.8
Classifier: Programming Language :: Python :: 3.9
